netknife/__init__.py
netknife/__main__.py
netknife/cli.py
netknife/utils.py
netknife/adapters/__init__.py
netknife/adapters/fortigate.py
netknife/commands/__init__.py
netknife/commands/address.py
netknife/commands/addrgrp.py
netknife/commands/policy.py
netknife/commands/probe.py
netknife/commands/quarantine.py
netknife/commands/smart.py
netknife/commands/vip.py
netknife-1.2.0.dist-info/METADATA
netknife-1.2.0.dist-info/WHEEL
netknife-1.2.0.dist-info/entry_points.txt
netknife-1.2.0.dist-info/licenses/LICENSE
netknife-1.2.0.dist-info/RECORD
