Metadata-Version: 2.4
Name: netknife
Version: 1.2.0
Summary: A CLI toolkit to manage FortiGate via REST API (policies, addresses, addrgrps, VIPs, etc.)
Project-URL: Homepage, https://github.com/yourname/netknife
Project-URL: Issues, https://github.com/yourname/netknife/issues
Author-email: "Berners.lk" <Berners.lk@gmail.com>
License:                                  Apache License
License-File: LICENSE
Keywords: api,cli,firewall,fortigate,network
Classifier: License :: OSI Approved :: MIT License
Classifier: Operating System :: OS Independent
Classifier: Programming Language :: Python :: 3
Classifier: Programming Language :: Python :: 3 :: Only
Classifier: Topic :: System :: Networking :: Firewalls
Requires-Python: >=3.8
Requires-Dist: requests>=2.28
Requires-Dist: urllib3>=1.26
